tick_streaming/__init__.py
tick_streaming/__version__.py
tick_streaming/utils.py
tick_streaming/stream/__init__.py
tick_streaming/stream/tick.py
tick_streaming/stream/ticks_store.py
tick_streaming/stream/stream_source/__init__.py
tick_streaming/stream/stream_source/base.py
tick_streaming/stream/stream_source/huobi.py
tick_streaming/stream/stream_source/internal.py
tick_streaming/stream/stream_source/mxc.py
tick_streaming/stream/stream_source/okex.py
tick_streaming/stream/stream_source/world.py
tick_streaming-0.0.4.dist-info/LICENSE
tick_streaming-0.0.4.dist-info/METADATA
tick_streaming-0.0.4.dist-info/WHEEL
tick_streaming-0.0.4.dist-info/top_level.txt
tick_streaming-0.0.4.dist-info/RECORD
